setup.py
ut95_distributions/Binomialdistribution.py
ut95_distributions/Gaussiandistribution.py
ut95_distributions/Generaldistribution.py
ut95_distributions/__init__.py
ut95_distributions.egg-info/PKG-INFO
ut95_distributions.egg-info/SOURCES.txt
ut95_distributions.egg-info/dependency_links.txt
ut95_distributions.egg-info/not-zip-safe
ut95_distributions.egg-info/top_level.txt