Metadata-Version: 1.0
Name: ut95-distributions
Version: 0.1
Summary: Gaussian and Binomial distributions
Home-page: UNKNOWN
Author: Usama Official
Author-email: usamaofficial95@gmail.com
License: UNKNOWN
Platform: UNKNOWN
